orgenex/__init__.py
orgenex/orgenex.py
orgenex-0.7.dist-info/METADATA
orgenex-0.7.dist-info/WHEEL
orgenex-0.7.dist-info/entry_points.txt
orgenex-0.7.dist-info/top_level.txt
orgenex-0.7.dist-info/RECORD
