Metadata-Version: 2.1
Name: orgenex
Version: 0.7
Summary: Converts an Evernote export to an emacs org-mode document
Home-page: https://bitbucket.org/tipmethewink/orgenex
Author: Mark Lee
Author-email: mark@droveend.com
License: UNKNOWN
Keywords: org-mode emacs evernote pandoc
Platform: UNKNOWN
Classifier: Programming Language :: Python :: 3
Classifier: License :: OSI Approved :: GNU General Public License v3 (GPLv3)
Classifier: Operating System :: OS Independent
Requires-Dist: Click
Requires-Dist: lxml
